lingua_franca/__init__.py
lingua_franca/bracket_expansion.py
lingua_franca/config.py
lingua_franca/format.py
lingua_franca/internal.py
lingua_franca/parse.py
lingua_franca/time.py
lingua_franca/lang/__init__.py
lingua_franca/lang/common_data_ca.py
lingua_franca/lang/common_data_cs.py
lingua_franca/lang/common_data_da.py
lingua_franca/lang/common_data_de.py
lingua_franca/lang/common_data_en.py
lingua_franca/lang/common_data_es.py
lingua_franca/lang/common_data_eu.py
lingua_franca/lang/common_data_fa.py
lingua_franca/lang/common_data_fr.py
lingua_franca/lang/common_data_hu.py
lingua_franca/lang/common_data_it.py
lingua_franca/lang/common_data_nl.py
lingua_franca/lang/common_data_pl.py
lingua_franca/lang/common_data_pt.py
lingua_franca/lang/common_data_ru.py
lingua_franca/lang/common_data_sl.py
lingua_franca/lang/common_data_sv.py
lingua_franca/lang/format_ca.py
lingua_franca/lang/format_common.py
lingua_franca/lang/format_cs.py
lingua_franca/lang/format_da.py
lingua_franca/lang/format_de.py
lingua_franca/lang/format_en.py
lingua_franca/lang/format_es.py
lingua_franca/lang/format_eu.py
lingua_franca/lang/format_fa.py
lingua_franca/lang/format_fr.py
lingua_franca/lang/format_hu.py
lingua_franca/lang/format_it.py
lingua_franca/lang/format_nl.py
lingua_franca/lang/format_pl.py
lingua_franca/lang/format_pt.py
lingua_franca/lang/format_ru.py
lingua_franca/lang/format_sl.py
lingua_franca/lang/format_sv.py
lingua_franca/lang/parse_ca.py
lingua_franca/lang/parse_common.py
lingua_franca/lang/parse_cs.py
lingua_franca/lang/parse_da.py
lingua_franca/lang/parse_de.py
lingua_franca/lang/parse_en.py
lingua_franca/lang/parse_es.py
lingua_franca/lang/parse_eu.py
lingua_franca/lang/parse_fa.py
lingua_franca/lang/parse_fr.py
lingua_franca/lang/parse_hu.py
lingua_franca/lang/parse_it.py
lingua_franca/lang/parse_nl.py
lingua_franca/lang/parse_pl.py
lingua_franca/lang/parse_pt.py
lingua_franca/lang/parse_ru.py
lingua_franca/lang/parse_sl.py
lingua_franca/lang/parse_sv.py
lingua_franca-0.4.3.dist-info/LICENSE
lingua_franca-0.4.3.dist-info/METADATA
lingua_franca-0.4.3.dist-info/WHEEL
lingua_franca-0.4.3.dist-info/top_level.txt
lingua_franca-0.4.3.dist-info/RECORD
