Metadata-Version: 2.1
Name: lingua-franca
Version: 0.4.3
Summary: Mycroft's multilingual text parsing and formatting library
Home-page: https://github.com/MycroftAI/lingua-franca
Author: Mycroft AI
Author-email: dev@mycroft.ai
License: Apache2.0
Platform: UNKNOWN
Classifier: Development Status :: 4 - Beta
Classifier: Intended Audience :: Developers
Classifier: Topic :: Text Processing :: Linguistic
Classifier: License :: OSI Approved :: Apache Software License
Classifier: Programming Language :: Python :: 3.7
Classifier: Programming Language :: Python :: 3.8
Classifier: Programming Language :: Python :: 3.9
Requires-Dist: python-dateutil (~=2.6.0)
